{"id":"index.html","dependencies":[{"name":"C:\\Users\\Tonderai Mutanda\\Desktop\\src\\package.json","includedInParent":true,"mtime":1531651461098},{"name":"./js\\main.js","dynamic":true,"parent":"C:\\Users\\Tonderai Mutanda\\Desktop\\src\\index.html","resolved":"C:\\Users\\Tonderai Mutanda\\Desktop\\src\\js\\main.js"}],"generated":{"html":"<!DOCTYPE html>\r\n<html lang=\"en\">\r\n<head>\r\n    <meta charset=\"UTF-8\">\r\n    <meta name=\"viewport\" content=\"width=device-width, initial-scale=1.0\">\r\n    <meta http-equiv=\"X-UA-Compatible\" content=\"ie=edge\">\r\n    <link href=\"https://stackpath.bootstrapcdn.com/bootstrap/4.1.2/css/bootstrap.min.css\" rel=\"stylesheet\" integrity=\"sha384-Smlep5jCw/wG7hdkwQ/Z5nLIefveQRIY9nfy6xoR1uRYBtpZgI6339F5dgvm/e9B\" crossorigin=\"anonymous\">\r\n    <title>Find Your Pet</title>\r\n</head>\r\n<body>\r\n    <header class=\"bg-light text-center mb-4 p3\">\r\n        <h3>find your pet</h3>\r\n    </header>\r\n    <div class=\"container\">\r\n        <form id=\"pet-form\">\r\n            <div class=\"form-group\">\r\n                <label for=\"animal\">Animal</label>\r\n                <select id=\"animal\" class=\"form-control form-control-lg mb-3\">\r\n                    <option value=\"cat\">Cat</option>\r\n                    <option value=\"dog\">Dog</option>\r\n                    <option value=\"bird\">Bird</option>\r\n                    <option value=\"barnyard\">Barnyard</option>\r\n                </select>\r\n                <input type=\"text\" id=\"zip\" class=\"form-control form-control-lg\" placeholder=\"Enter your zipcode\">\r\n                <input type=\"submit\" value=\"Find\" class=\"btn btn-dark btn-lg btn-block mt-3\">\r\n            </div>\r\n        </form>\r\n\r\n        <div id=\"results\"></div>\r\n    </div>\r\n\r\n    <script src=\"/60e8c532b6c719a5707f85872b55488a.js\"></script>\r\n</body>\r\n</html>"},"hash":"6fcf7ce6f210463579fc4c9e53684a4f","cacheData":{}}